Metadata-Version: 2.1
Name: urban-mapper
Version: 0.1.5
Summary: 🗺️ Spatial Join & Enrich any urban layer given any external urban dataset of interest, streamline your urban analysis with Scikit-Learn-Like pipelines, and share your insights with the urban research community!
Author-Email: Provost Simon <sgp29@kent.ac.uk>, New York University <fairuse@nyu.edu>
License: MIT
Classifier: Development Status :: 4 - Beta
Classifier: Intended Audience :: Developers
Classifier: Programming Language :: Python
Classifier: Programming Language :: Python :: 3
Classifier: Programming Language :: Python :: 3 :: Only
Classifier: Programming Language :: Python :: 3.9
Classifier: Programming Language :: Python :: 3.10
Classifier: Programming Language :: Python :: 3.11
Classifier: Programming Language :: Python :: 3.12
Classifier: Programming Language :: Python :: 3.13
Classifier: Programming Language :: Python :: 3.14
Classifier: Topic :: Documentation
Classifier: Topic :: Software Development
Classifier: Topic :: Utilities
Classifier: Typing :: Typed
Project-URL: Homepage, https://github.com/VIDA-NYU/UrbanMapper
Project-URL: Documentation, https://urbanmapper.readthedocs.io/en/latest/
Project-URL: Changelog, https://github.com/VIDA-NYU/UrbanMapper/blob/main/CHANGELOG.md
Project-URL: Repository, https://github.com/VIDA-NYU/UrbanMapper
Project-URL: Issues, https://github.com/VIDA-NYU/UrbanMapper/issues
Project-URL: Discussions, https://github.com/VIDA-NYU/UrbanMapper/discussions
Requires-Python: >=3.10
Requires-Dist: folium>=0.19.4
Requires-Dist: ipython>=8.18.1
Requires-Dist: ipywidgets>=8.1.5
Requires-Dist: matplotlib>=3.9.4
Requires-Dist: networkx>=3.2.1
Requires-Dist: scikit-learn>=1.6.1
Requires-Dist: beartype>=0.19.0
Requires-Dist: osmnx>=2.0.1
Requires-Dist: geopandas>=1.0.1
Requires-Dist: dependency-injector>=4.45.0
Requires-Dist: pyarrow>=19.0.1
Requires-Dist: loguru>=0.7.3
Requires-Dist: thefuzz>=0.22.1
Requires-Dist: dill<0.3.8
Requires-Dist: geopy>=2.4.1
Requires-Dist: alive-progress>=3.2.0
Requires-Dist: datasets>=3.5.0
Requires-Dist: mapclassify>=2.8.1
Provides-Extra: notebook
Requires-Dist: jupyter>=1.1.1; extra == "notebook"
Requires-Dist: notebook==6.4.12; extra == "notebook"
Requires-Dist: jupyter-server-ydoc>=1.1.0; extra == "notebook"
Requires-Dist: jupyter-contrib-nbextensions>=0.7.0; extra == "notebook"
Requires-Dist: jupyterlab-widgets>=3.0.13; extra == "notebook"
Requires-Dist: jupyter-resource-usage>=1.1.1; extra == "notebook"
Requires-Dist: nbstripout>=0.8.1; extra == "notebook"
Provides-Extra: interactive-table-vis
Requires-Dist: skrub>=0.5.1; extra == "interactive-table-vis"
Provides-Extra: auctus-mixins
Requires-Dist: auctus-search; extra == "auctus-mixins"
Provides-Extra: pipeline-generators
Requires-Dist: ell-ai[all]>=0.0.17; extra == "pipeline-generators"
Provides-Extra: jupytergis-mixins
Requires-Dist: jupytergis==0.4.4; extra == "jupytergis-mixins"
Requires-Dist: jupytergis-core>=0.2.1; extra == "jupytergis-mixins"
Requires-Dist: jupytergis-qgis>=0.2.1; extra == "jupytergis-mixins"
Provides-Extra: full
Requires-Dist: skrub>=0.5.1; extra == "full"
Requires-Dist: auctus-search; extra == "full"
Requires-Dist: ell-ai[all]>=0.0.17; extra == "full"
Requires-Dist: jupyter>=1.1.1; extra == "full"
Requires-Dist: notebook==6.4.12; extra == "full"
Requires-Dist: jupyter-server-ydoc>=1.1.0; extra == "full"
Requires-Dist: jupyter-contrib-nbextensions>=0.7.0; extra == "full"
Requires-Dist: jupyterlab-widgets>=3.0.13; extra == "full"
Requires-Dist: jupyter-resource-usage>=1.1.1; extra == "full"
Requires-Dist: nbstripout>=0.8.1; extra == "full"
Requires-Dist: jupytergis==0.4.4; extra == "full"
Requires-Dist: jupytergis-core>=0.2.1; extra == "full"
Requires-Dist: jupytergis-qgis>=0.2.1; extra == "full"
